bermuda/__about__.py
bermuda/__init__.py
bermuda/date_utils.py
bermuda/errors.py
bermuda/factory.py
bermuda/meyers.trib
bermuda/plot.py
bermuda/triangle.py
bermuda/base/__init__.py
bermuda/base/cell.py
bermuda/base/incremental.py
bermuda/base/metadata.py
bermuda/io/__init__.py
bermuda/io/array.py
bermuda/io/binary.py
bermuda/io/binary_input.py
bermuda/io/binary_output.py
bermuda/io/chain_ladder.py
bermuda/io/data_frame_input.py
bermuda/io/data_frame_output.py
bermuda/io/json.py
bermuda/io/matrix.py
bermuda/io/rich_matrix.py
bermuda/matrix/__init__.py
bermuda/matrix/index.py
bermuda/matrix/matrix.py
bermuda/utils/__init__.py
bermuda/utils/adjust.py
bermuda/utils/aggregate.py
bermuda/utils/backfill.py
bermuda/utils/basis.py
bermuda/utils/bootstrap.py
bermuda/utils/currency.py
bermuda/utils/disaggregate.py
bermuda/utils/extend.py
bermuda/utils/fields.py
bermuda/utils/fill.py
bermuda/utils/join.py
bermuda/utils/merge.py
bermuda/utils/method_moments.py
bermuda/utils/premium_pattern.py
bermuda/utils/shift_origin.py
bermuda/utils/slice.py
bermuda/utils/summarize.py
bermuda/utils/thin.py
bermuda_ledger-2.1.29.dist-info/METADATA
bermuda_ledger-2.1.29.dist-info/WHEEL
bermuda_ledger-2.1.29.dist-info/licenses/LICENSE.txt
bermuda_ledger-2.1.29.dist-info/RECORD
